rests/__init__.py
rests-0.0.1.dist-info/LICENSE
rests-0.0.1.dist-info/WHEEL
rests-0.0.1.dist-info/METADATA
rests-0.0.1.dist-info/RECORD
