Metadata-Version: 2.1
Name: rests
Version: 0.0.1
Summary: Framework independent REST the way it should be! 
Home-page: https://rests.readthedocs.io
License: BSD-3-Clause
Author: sobolevn
Author-email: mail@sobolevn.me
Requires-Python: >=3.7,<4.0
Classifier: License :: OSI Approved :: BSD License
Classifier: Programming Language :: Python :: 3
Classifier: Programming Language :: Python :: 3.7
Classifier: Programming Language :: Python :: 3.8
Project-URL: Funding, https://github.com/sponsors/dry-python
Project-URL: Repository, https://github.com/dry-python/rests
